someip_catch/__init__.py
someip_catch/data/document.7z
someip_catch-1.0.0.dist-info/METADATA
someip_catch-1.0.0.dist-info/WHEEL
someip_catch-1.0.0.dist-info/top_level.txt
someip_catch-1.0.0.dist-info/RECORD
