Metadata-Version: 2.1
Name: someip-catch
Version: 1.0.0
Summary: SOME/IP协议捕获和分析工具包
Home-page: https://github.com/yourusername/someip-catch
Author: SOME/IP Catch Framework
Project-URL: Repository, https://github.com/yourusername/someip-catch
Keywords: someip automotive network protocol catch analysis
Classifier: Development Status :: 4 - Beta
Classifier: Intended Audience :: Developers
Classifier: Programming Language :: Python :: 3
Classifier: Programming Language :: Python :: 3.7
Classifier: Programming Language :: Python :: 3.8
Classifier: Programming Language :: Python :: 3.9
Classifier: Programming Language :: Python :: 3.10
Classifier: Programming Language :: Python :: 3.11
Classifier: Topic :: Software Development :: Libraries :: Python Modules
Classifier: Topic :: System :: Networking
Classifier: Topic :: System :: Hardware
Requires-Python: >=3.7
